regex_compose.py
regex_compose-0.0.3.dist-info/LICENSE
regex_compose-0.0.3.dist-info/METADATA
regex_compose-0.0.3.dist-info/WHEEL
regex_compose-0.0.3.dist-info/top_level.txt
regex_compose-0.0.3.dist-info/RECORD
