Metadata-Version: 2.1
Name: regex-compose
Version: 0.0.3
Summary: Compose multiple regular expressions into one using a special syntax
Author: Shae.c32
Project-URL: Homepage, https://codeberg.org/Shae/RegExCompose
Project-URL: Issues, https://codeberg.org/Shae/RegExCompose/issues
Keywords: re,regex,regular,expression
Classifier: Development Status :: 4 - Beta
Classifier: Intended Audience :: Developers
Classifier: License :: OSI Approved :: Apache Software License
Classifier: Natural Language :: English
Classifier: Operating System :: OS Independent
Classifier: Programming Language :: Python :: 3
Classifier: Topic :: Software Development :: Compilers
Classifier: Topic :: Software Development :: Interpreters
Classifier: Topic :: Software Development :: Libraries :: Python Modules
Classifier: Topic :: Software Development :: Pre-processors
Classifier: Topic :: Text Processing
Classifier: Topic :: Utilities
Classifier: Typing :: Typed
Requires-Python: >=3.9
License-File: LICENSE
